ethtools/__init__.py
ethtools/eth_properties.py
ethtools/eth_tools.py
ethtools/eth_types.py
ethtools/server/__init__.py
ethtools/server/web_server.py
ethtools/server/accounts/__init__.py
ethtools/server/accounts/account_context.py
ethtools/server/accounts/account_manager.py
ethtools/server/accounts/account_rest.py
ethtools/server/contracts/__init__.py
ethtools/server/contracts/contract_context.py
ethtools/server/contracts/contract_manager.py
ethtools/server/contracts/contract_rest.py
ethtools-1.0.7.dist-info/LICENSE
ethtools-1.0.7.dist-info/METADATA
ethtools-1.0.7.dist-info/WHEEL
ethtools-1.0.7.dist-info/top_level.txt
ethtools-1.0.7.dist-info/RECORD
